.travis.yml
CHANGES.rst
MANIFEST.in
README.rst
bootstrap.py
buildout.cfg
setup.py
tox.ini
src/keas/__init__.py
src/keas.profile.egg-info/PKG-INFO
src/keas.profile.egg-info/SOURCES.txt
src/keas.profile.egg-info/dependency_links.txt
src/keas.profile.egg-info/entry_points.txt
src/keas.profile.egg-info/namespace_packages.txt
src/keas.profile.egg-info/not-zip-safe
src/keas.profile.egg-info/requires.txt
src/keas.profile.egg-info/top_level.txt
src/keas/profile/README.txt
src/keas/profile/__init__.py
src/keas/profile/profiler.py
src/keas/profile/tests.py