Metadata-Version: 1.1
Name: keas.profile
Version: 0.3.0
Summary: WSGI Profiler for Python Paste
Home-page: http://pypi.python.org/pypi/keas.profile
Author: Marius Gedminas and the Zope Community.
Author-email: zope-dev@zope.org
License: ZPL 2.1
Keywords: zope3 profile paste wsgi
Platform: UNKNOWN
Classifier: Development Status :: 4 - Beta
Classifier: Environment :: Web Environment
Classifier: Intended Audience :: Developers
Classifier: License :: OSI Approved :: Zope Public License
Classifier: Programming Language :: Python :: 2.6
Classifier: Programming Language :: Python :: 2.7
Classifier: Programming Language :: Python :: 3.2
Classifier: Programming Language :: Python :: 3.3
Classifier: Programming Language :: Python :: Implementation :: CPython
Classifier: Programming Language :: Python :: Implementation :: PyPy
Classifier: Natural Language :: English
Classifier: Operating System :: OS Independent
Classifier: Topic :: Internet :: WWW/HTTP
Classifier: Framework :: Zope3
